xaib/__init__.py
xaib/base/__init__.py
xaib/base/base.py
xaib/cases/__init__.py
xaib/cases/example_selection/__init__.py
xaib/cases/example_selection/continuity_case.py
xaib/cases/example_selection/contrastivity_case.py
xaib/cases/example_selection/correctness_case.py
xaib/cases/example_selection/covariate_complexity_case.py
xaib/cases/feature_importance/__init__.py
xaib/cases/feature_importance/coherence_case.py
xaib/cases/feature_importance/compactness_case.py
xaib/cases/feature_importance/continuity_case.py
xaib/cases/feature_importance/contrastivity_case.py
xaib/cases/feature_importance/correctness_case.py
xaib/cases/feature_importance/covariate_complexity_case.py
xaib/datasets/__init__.py
xaib/datasets/sk_dataset.py
xaib/datasets/synthetic_dataset.py
xaib/evaluation/__init__.py
xaib/evaluation/dataset_factory.py
xaib/evaluation/model_factory.py
xaib/evaluation/utils.py
xaib/evaluation/example_selection/__init__.py
xaib/evaluation/example_selection/case_factory.py
xaib/evaluation/example_selection/example_selection.py
xaib/evaluation/example_selection/experiment_factory.py
xaib/evaluation/example_selection/explainer_factory.py
xaib/evaluation/feature_importance/__init__.py
xaib/evaluation/feature_importance/case_factory.py
xaib/evaluation/feature_importance/experiment_factory.py
xaib/evaluation/feature_importance/explainer_factory.py
xaib/evaluation/feature_importance/feature_importance.py
xaib/explainers/__init__.py
xaib/explainers/example_selection/__init__.py
xaib/explainers/example_selection/constant_explainer.py
xaib/explainers/example_selection/knn_explainer.py
xaib/explainers/example_selection/random_explainer.py
xaib/explainers/feature_importance/__init__.py
xaib/explainers/feature_importance/constant_explainer.py
xaib/explainers/feature_importance/lime_explainer.py
xaib/explainers/feature_importance/linear_regression_explainer.py
xaib/explainers/feature_importance/random_explainer.py
xaib/explainers/feature_importance/shap_explainer.py
xai_benchmark-0.3.0.dist-info/LICENSE
xai_benchmark-0.3.0.dist-info/METADATA
xai_benchmark-0.3.0.dist-info/WHEEL
xai_benchmark-0.3.0.dist-info/top_level.txt
xai_benchmark-0.3.0.dist-info/RECORD
