Metadata-Version: 2.1
Name: xai-benchmark
Version: 0.3.0
Summary: Benchmark for Explainable AI methods
Home-page: https://github.com/oxid15/xai-benchmark
Author: Ilia Moiseev
Author-email: ilia.moiseev.5@yandex.ru
License: MIT
Classifier: Programming Language :: Python :: 3
Classifier: Operating System :: OS Independent
Requires-Python: >=3.8
License-File: LICENSE
Requires-Dist: cascade-ml
Requires-Dist: scikit-learn
Requires-Dist: plotly
Requires-Dist: kaleido
